MANIFEST.in
README.md
setup.cfg
setup.py
gcam_reader/__init__.py
gcam_reader/querymi.py
gcam_reader.egg-info/PKG-INFO
gcam_reader.egg-info/SOURCES.txt
gcam_reader.egg-info/dependency_links.txt
gcam_reader.egg-info/not-zip-safe
gcam_reader.egg-info/requires.txt
gcam_reader.egg-info/top_level.txt
gcam_reader/ModelInterface/Main_queries.xml
gcam_reader/ModelInterface/ModelInterface.jar
gcam_reader/ModelInterface/batch-prototype.xml
gcam_reader/ModelInterface/batch-sample.xml
gcam_reader/ModelInterface/model_interface.properties
gcam_reader/ModelInterface/sample-queries-interactive.xml
gcam_reader/ModelInterface/sample-queries.xml
gcam_reader/ModelInterface/sample.csv
gcam_reader/ModelInterface/sample_with_errors.csv
gcam_reader/ModelInterface/jars/BaseX-9.5.0.jar
gcam_reader/tests/__init__.py
gcam_reader/tests/test_querymi.py
gcam_reader/tests/data/comp_outputs/land_query.csv
gcam_reader/tests/data/queries/query_land_reg32_basin235_gcam5p0.xml
gcam_reader/tests/data/sample_basexdb/atv.basex
gcam_reader/tests/data/sample_basexdb/inf.basex
gcam_reader/tests/data/sample_basexdb/tbl.basex
gcam_reader/tests/data/sample_basexdb/tbli.basex
gcam_reader/tests/data/sample_basexdb/txt.basex
gcam_reader/tests/data/sample_basexdb/txtl.basex
gcam_reader/tests/data/sample_basexdb/txtr.basex