Metadata-Version: 1.2
Name: gcam-reader
Version: 1.2.1
Summary: Tools for importing GCAM output data
Home-page: https://github.com/JGCRI/gcam_reader
Author: Robert Link
Author-email: robert.link@pnnl.gov
License: BSD 2-Clause
Platform: UNKNOWN
Requires-Python: >=3.6
